odoo10_addon_procurement_purchase_no_grouping-10.0.1.0.0-py2.7-nspkg.pth
odoo/addons/procurement_purchase_no_grouping/README.rst
odoo/addons/procurement_purchase_no_grouping/__init__.py
odoo/addons/procurement_purchase_no_grouping/__manifest__.py
odoo/addons/procurement_purchase_no_grouping/i18n/de.po
odoo/addons/procurement_purchase_no_grouping/i18n/es.po
odoo/addons/procurement_purchase_no_grouping/i18n/es_ES.po
odoo/addons/procurement_purchase_no_grouping/i18n/es_MX.po
odoo/addons/procurement_purchase_no_grouping/i18n/fi.po
odoo/addons/procurement_purchase_no_grouping/i18n/fr.po
odoo/addons/procurement_purchase_no_grouping/i18n/fr_FR.po
odoo/addons/procurement_purchase_no_grouping/i18n/gl.po
odoo/addons/procurement_purchase_no_grouping/i18n/hr.po
odoo/addons/procurement_purchase_no_grouping/i18n/it.po
odoo/addons/procurement_purchase_no_grouping/i18n/nl.po
odoo/addons/procurement_purchase_no_grouping/i18n/nl_NL.po
odoo/addons/procurement_purchase_no_grouping/i18n/pt_BR.po
odoo/addons/procurement_purchase_no_grouping/i18n/pt_PT.po
odoo/addons/procurement_purchase_no_grouping/i18n/ro.po
odoo/addons/procurement_purchase_no_grouping/i18n/sl.po
odoo/addons/procurement_purchase_no_grouping/i18n/tr_TR.po
odoo/addons/procurement_purchase_no_grouping/i18n/vi_VN.po
odoo/addons/procurement_purchase_no_grouping/i18n/zh_CN.po
odoo/addons/procurement_purchase_no_grouping/models/__init__.py
odoo/addons/procurement_purchase_no_grouping/models/procurement_order.py
odoo/addons/procurement_purchase_no_grouping/models/product_category.py
odoo/addons/procurement_purchase_no_grouping/models/purchase_order.py
odoo/addons/procurement_purchase_no_grouping/tests/__init__.py
odoo/addons/procurement_purchase_no_grouping/tests/test_procurement_purchase_no_grouping.py
odoo/addons/procurement_purchase_no_grouping/views/product_category_view.xml
odoo10_addon_procurement_purchase_no_grouping-10.0.1.0.0.dist-info/DESCRIPTION.rst
odoo10_addon_procurement_purchase_no_grouping-10.0.1.0.0.dist-info/METADATA
odoo10_addon_procurement_purchase_no_grouping-10.0.1.0.0.dist-info/RECORD
odoo10_addon_procurement_purchase_no_grouping-10.0.1.0.0.dist-info/WHEEL
odoo10_addon_procurement_purchase_no_grouping-10.0.1.0.0.dist-info/metadata.json
odoo10_addon_procurement_purchase_no_grouping-10.0.1.0.0.dist-info/namespace_packages.txt
odoo10_addon_procurement_purchase_no_grouping-10.0.1.0.0.dist-info/top_level.txt
