Metadata-Version: 2.0
Name: odoo10-addon-procurement-purchase-no-grouping
Version: 10.0.1.0.0
Summary: Procurement Purchase No Grouping
Home-page: https://github.com/OCA/purchase-workflow
Author: AvanzOSC,Tecnativa,Odoo Community Association (OCA)
Author-email: support@odoo-community.org
License: AGPL-3
Platform: UNKNOWN
Classifier: Programming Language :: Python :: 2.7
Classifier: Framework :: Odoo
Classifier: License :: OSI Approved :: GNU Affero General Public License v3
Requires-Dist: odoo (<10.1dev,>=10.0)
